messytables/__init__.py
messytables/any.py
messytables/commas.py
messytables/compat23.py
messytables/core.py
messytables/dateparser.py
messytables/error.py
messytables/excel.py
messytables/headers.py
messytables/html.py
messytables/jts.py
messytables/ods.py
messytables/types.py
messytables/util.py
messytables/zip.py
python_messytable_handler-0.2.3.dist-info/METADATA
python_messytable_handler-0.2.3.dist-info/WHEEL
python_messytable_handler-0.2.3.dist-info/top_level.txt
python_messytable_handler-0.2.3.dist-info/RECORD
